{
  "colorHoney700": "#CC8800",
  "colorHoney600": "#FFAA00",
  "colorHoney500": "#FFBE3C",
  "colorHoney400": "#FFCC66",
  "colorHoney300": "#FFDD99",
  "colorHoney200": "#FFEECC",
  "colorHoney100": "#FFF7E6",
  "colorTropical700": "#003D3D",
  "colorTropical600": "#005757",
  "colorTropical500": "#007171",
  "colorTropical400": "#338D8D",
  "colorTropical300": "#66AAAA",
  "colorTropical200": "#99C6C6",
  "colorTropical100": "#CCE3E3",
  "colorTropical50": "#E5F1F1",
  "colorStormy600": "#061927",
  "colorStormy500": "#0A273D",
  "colorStormy400": "#3B5264",
  "colorStormy300": "#677784",
  "colorStormy200": "#7F8F99",
  "colorStormy100": "#9CA8B0",
  "colorSnow800": "#C6CDD2",
  "colorSnow700": "#D4DADD",
  "colorSnow600": "#E3E6E8",
  "colorSnow500": "#F1F3F4",
  "colorSnow100": "#FFFFFF",
  "colorRaspberry700": "#881125",
  "colorRaspberry600": "#B61631",
  "colorRaspberry500": "#E31C3D",
  "colorRaspberry400": "#E94964",
  "colorRaspberry300": "#EE778B",
  "colorRaspberry200": "#F4A4B1",
  "colorRaspberry100": "#F9D2D8",
  "colorRaspberry50": "#FCE8EB",
  "colorTextDefault": "#0A273D",
  "colorTextInverted": "#FFFFFF",
  "colorTextMuted": "#677784",
  "colorTextLink": "#007171",
  "colorTextInvalid": "#E31C3D",
  "colorError800": "#57000E",
  "colorError500": "#E31C3D",
  "colorError200": "#FCD7D4",
  "colorSuccess700": "#005419",
  "colorSuccess500": "#2E8540",
  "colorSuccess200": "#D7F1D8",
  "colorInformative700": "#003B7E",
  "colorInformative500": "#2071CE",
  "colorInformative200": "#D5E5F8",
  "colorWarning700": "#9C2E00",
  "colorWarning500": "#F35B1C",
  "colorWarning200": "#FFE8D6",
  "colorNight400": "#3247E9",
  "colorNight200": "#D1D6FA",
  "colorAqua400": "#3DAED8",
  "colorAqua200": "#AADBEE",
  "colorGrass400": "#39B93D",
  "colorGrass200": "#B4E4B5",
  "colorDirt400": "#828282",
  "colorDirt200": "#E0DDDC",
  "colorBerry400": "#F95252",
  "colorBerry200": "#FCA7A7",
  "colorCandy400": "#E467C3",
  "colorCandy200": "#F6CBEA",
  "colorMud400": "#8B6559",
  "colorMud200": "#D7C6C1",
  "colorOrange400": "#FF8C34",
  "colorOrange200": "#FFD4B3",
  "colorBolt400": "#FFBE3C",
  "colorBolt200": "#FFE6B3",
  "colorBackgroundGrey": "#FAFAFA",
  "colorBackgroundGreen": "#DCEDE1",
  "colorBackgroundBlue": "#DEF2FF",
  "colorBackgroundYellow": "#FCECCB",
  "colorBackgroundWhite": "#FFFFFF"
}
